torchopt/__init__.py
torchopt/base.py
torchopt/clip.py
torchopt/combine.py
torchopt/hook.py
torchopt/py.typed
torchopt/pytree.py
torchopt/typing.py
torchopt/update.py
torchopt/utils.py
torchopt/version.py
torchopt/visual.py
torchopt/_C/adam_op.pyi
torchopt/accelerated_op/__init__.py
torchopt/accelerated_op/adam_op.py
torchopt/accelerated_op/_src/__init__.py
torchopt/accelerated_op/_src/adam_op.py
torchopt/alias/__init__.py
torchopt/alias/adadelta.py
torchopt/alias/adagrad.py
torchopt/alias/adam.py
torchopt/alias/adamax.py
torchopt/alias/adamw.py
torchopt/alias/radam.py
torchopt/alias/rmsprop.py
torchopt/alias/sgd.py
torchopt/alias/utils.py
torchopt/diff/__init__.py
torchopt/diff/implicit/__init__.py
torchopt/diff/implicit/decorator.py
torchopt/diff/implicit/nn/__init__.py
torchopt/diff/implicit/nn/module.py
torchopt/diff/zero_order/__init__.py
torchopt/diff/zero_order/decorator.py
torchopt/diff/zero_order/nn/__init__.py
torchopt/diff/zero_order/nn/module.py
torchopt/distributed/__init__.py
torchopt/distributed/api.py
torchopt/distributed/autograd.py
torchopt/distributed/world.py
torchopt/linalg/__init__.py
torchopt/linalg/cg.py
torchopt/linalg/ns.py
torchopt/linalg/utils.py
torchopt/linear_solve/__init__.py
torchopt/linear_solve/cg.py
torchopt/linear_solve/inv.py
torchopt/linear_solve/normal_cg.py
torchopt/linear_solve/utils.py
torchopt/nn/__init__.py
torchopt/nn/module.py
torchopt/nn/stateless.py
torchopt/optim/__init__.py
torchopt/optim/adadelta.py
torchopt/optim/adagrad.py
torchopt/optim/adam.py
torchopt/optim/adamax.py
torchopt/optim/adamw.py
torchopt/optim/base.py
torchopt/optim/radam.py
torchopt/optim/rmsprop.py
torchopt/optim/sgd.py
torchopt/optim/func/__init__.py
torchopt/optim/func/base.py
torchopt/optim/meta/__init__.py
torchopt/optim/meta/adadelta.py
torchopt/optim/meta/adagrad.py
torchopt/optim/meta/adam.py
torchopt/optim/meta/adamax.py
torchopt/optim/meta/adamw.py
torchopt/optim/meta/base.py
torchopt/optim/meta/radam.py
torchopt/optim/meta/rmsprop.py
torchopt-0.7.3.dist-info/LICENSE
torchopt-0.7.3.dist-info/METADATA
torchopt-0.7.3.dist-info/WHEEL
torchopt-0.7.3.dist-info/top_level.txt
torchopt-0.7.3.dist-info/RECORD
