Metadata-Version: 2.1
Name: torchopt
Version: 0.7.3
Summary: An efficient library for differentiable optimization for PyTorch.
Author: TorchOpt Contributors
Author-email: Jie Ren <jieren9806@gmail.com>, Xidong Feng <xidong.feng.20@ucl.ac.uk>, Bo Liu <benjaminliu.eecs@gmail.com>, Xuehai Pan <XuehaiPan@pku.edu.cn>
License: Apache License, Version 2.0
Project-URL: Homepage, https://github.com/metaopt/torchopt
Project-URL: Repository, https://github.com/metaopt/torchopt
Project-URL: Documentation, https://torchopt.readthedocs.io
Project-URL: Bug Report, https://github.com/metaopt/torchopt/issues
Keywords: PyTorch,functorch,JAX,Meta-Learning,Optimizer,Differentiable Optimizer,Functional Programming
Classifier: Development Status :: 4 - Beta
Classifier: License :: OSI Approved :: Apache Software License
Classifier: Programming Language :: Python :: 3
Classifier: Programming Language :: Python :: 3.8
Classifier: Programming Language :: Python :: 3.9
Classifier: Programming Language :: Python :: 3.10
Classifier: Programming Language :: Python :: 3.11
Classifier: Operating System :: Microsoft :: Windows
Classifier: Operating System :: POSIX :: Linux
Classifier: Operating System :: MacOS
Classifier: Environment :: GPU
Classifier: Environment :: GPU :: NVIDIA CUDA
Classifier: Intended Audience :: Developers
Classifier: Intended Audience :: Education
Classifier: Intended Audience :: Science/Research
Classifier: Topic :: Scientific/Engineering
Classifier: Topic :: Scientific/Engineering :: Artificial Intelligence
Requires-Python: >=3.8
License-File: LICENSE
Requires-Dist: torch >=1.13
Requires-Dist: optree >=0.4.1
Requires-Dist: numpy
Requires-Dist: graphviz
Requires-Dist: typing-extensions >=4.0.0
Provides-Extra: lint
Requires-Dist: isort ; extra == 'lint'
Requires-Dist: black[jupyter] >=22.6.0 ; extra == 'lint'
Requires-Dist: pylint[spelling] >=2.15.0 ; extra == 'lint'
Requires-Dist: mypy >=0.990 ; extra == 'lint'
Requires-Dist: flake8 ; extra == 'lint'
Requires-Dist: flake8-bugbear ; extra == 'lint'
Requires-Dist: flake8-comprehensions ; extra == 'lint'
Requires-Dist: flake8-docstrings ; extra == 'lint'
Requires-Dist: flake8-pyi ; extra == 'lint'
Requires-Dist: flake8-simplify ; extra == 'lint'
Requires-Dist: ruff ; extra == 'lint'
Requires-Dist: doc8 ; extra == 'lint'
Requires-Dist: pydocstyle[toml] ; extra == 'lint'
Requires-Dist: pyenchant ; extra == 'lint'
Requires-Dist: cpplint ; extra == 'lint'
Requires-Dist: pre-commit ; extra == 'lint'
Provides-Extra: test
Requires-Dist: pytest ; extra == 'test'
Requires-Dist: pytest-cov ; extra == 'test'
Requires-Dist: pytest-xdist ; extra == 'test'
Requires-Dist: jax[cpu] >=0.3 ; (platform_system != "Windows") and extra == 'test'
Requires-Dist: jaxopt ; (platform_system != "Windows") and extra == 'test'
Requires-Dist: optax ; (platform_system != "Windows") and extra == 'test'
